meaningful_pdf_names/__init__.py
meaningful_pdf_names/__main__.py
meaningful_pdf_names/cli.py
meaningful_pdf_names-0.2.1.dist-info/licenses/LICENSE
tests/__init__.py
tests/test_integration.py
tests/test_page_count.py
meaningful_pdf_names-0.2.1.dist-info/METADATA
meaningful_pdf_names-0.2.1.dist-info/WHEEL
meaningful_pdf_names-0.2.1.dist-info/entry_points.txt
meaningful_pdf_names-0.2.1.dist-info/top_level.txt
meaningful_pdf_names-0.2.1.dist-info/RECORD
