Metadata-Version: 2.4
Name: meaningful-pdf-names
Version: 0.2.1
Summary: Offline-friendly PDF renamer that generates meaningful, keyword-rich filenames from PDF content.
Author-email: Nishant Kumar <abcnishant007@gmail.com>
License: MIT
Project-URL: Homepage, https://github.com/abcnishant007/meaningful-pdf-names
Project-URL: Source, https://github.com/abcnishant007/meaningful-pdf-names
Project-URL: Issues, https://github.com/abcnishant007/meaningful-pdf-names/issues
Keywords: pdf,rename,keywords,offline,cli
Classifier: Programming Language :: Python :: 3
Classifier: License :: OSI Approved :: MIT License
Classifier: Operating System :: OS Independent
Classifier: Topic :: Utilities
Classifier: Topic :: Text Processing :: Linguistic
Requires-Python: >=3.9
License-File: LICENSE
Requires-Dist: pypdf>=5.0.0
Provides-Extra: summarizer
Requires-Dist: transformers>=4.45.0; extra == "summarizer"
Requires-Dist: torch>=2.0.0; extra == "summarizer"
Dynamic: license-file
